{
  "options": [
    {
      "ticker": "MU",
      "action": "Buy",
      "horizon": "swing_term",
      "thesis": "Medium-term trend with revenue/EPS growth, sector leadership, and supportive ownership.",
      "equity_entry": 399.5679,
      "underlying_price": 397.58,
      "best_call": {
        "put_call": "CALL",
        "symbol": "MU    260206C00397500",
        "strike": 397.5,
        "expiration": "2026-02-06T21:00:00+00:00",
        "days_to_expiration": 14,
        "target_dte": 45,
        "bid": 21.5,
        "ask": 22.35,
        "mid": 21.925,
        "mark": 21.93,
        "last": 22.1,
        "open_interest": 39,
        "volume": null,
        "delta": 0.524,
        "gamma": 0.007,
        "theta": -0.717,
        "vega": 0.32,
        "rho": 0.073,
        "implied_volatility": 67.401,
        "in_the_money": true,
        "spread": 0.8500000000000014,
        "spread_pct": 3.876852907639687,
        "break_even": 419.425,
        "moneyness_pct": -0.02012173650585645,
        "description": "MU 02/06/2026 397.50 C"
      },
      "best_put": {
        "put_call": "PUT",
        "symbol": "MU    260206P00397500",
        "strike": 397.5,
        "expiration": "2026-02-06T21:00:00+00:00",
        "days_to_expiration": 14,
        "target_dte": 45,
        "bid": 21.1,
        "ask": 22.5,
        "mid": 21.8,
        "mark": 21.8,
        "last": 22.45,
        "open_interest": 2,
        "volume": null,
        "delta": -0.476,
        "gamma": 0.007,
        "theta": -0.751,
        "vega": 0.32,
        "rho": -0.086,
        "implied_volatility": 67.401,
        "in_the_money": false,
        "spread": 1.3999999999999986,
        "spread_pct": 6.422018348623847,
        "break_even": 375.7,
        "moneyness_pct": -0.02012173650585645,
        "description": "MU 02/06/2026 397.50 P"
      },
      "call_candidates": 168,
      "put_candidates": 168,
      "warnings": [],
      "chain_error": null
    },
    {
      "ticker": "INTC",
      "action": "Buy",
      "horizon": "swing_term",
      "thesis": "Medium-term trend with revenue/EPS growth, sector leadership, and supportive ownership.",
      "equity_entry": 54.5916,
      "underlying_price": 54.32,
      "best_call": {
        "put_call": "CALL",
        "symbol": "INTC  260306C00054000",
        "strike": 54.0,
        "expiration": "2026-03-06T21:00:00+00:00",
        "days_to_expiration": 42,
        "target_dte": 45,
        "bid": 5.0,
        "ask": 5.35,
        "mid": 5.175,
        "mark": 5.18,
        "last": 5.3,
        "open_interest": 82,
        "volume": null,
        "delta": 0.552,
        "gamma": 0.032,
        "theta": -0.055,
        "vega": 0.073,
        "rho": 0.028,
        "implied_volatility": 65.31,
        "in_the_money": true,
        "spread": 0.34999999999999964,
        "spread_pct": 6.763285024154583,
        "break_even": 59.175,
        "moneyness_pct": -0.5891016200294555,
        "description": "INTC 03/06/2026 54.00 C"
      },
      "best_put": {
        "put_call": "PUT",
        "symbol": "INTC  260306P00054000",
        "strike": 54.0,
        "expiration": "2026-03-06T21:00:00+00:00",
        "days_to_expiration": 42,
        "target_dte": 45,
        "bid": 4.6,
        "ask": 4.8,
        "mid": 4.699999999999999,
        "mark": 4.7,
        "last": 4.6,
        "open_interest": 25,
        "volume": null,
        "delta": -0.447,
        "gamma": 0.032,
        "theta": -0.057,
        "vega": 0.074,
        "rho": -0.034,
        "implied_volatility": 65.31,
        "in_the_money": false,
        "spread": 0.20000000000000018,
        "spread_pct": 4.255319148936175,
        "break_even": 49.3,
        "moneyness_pct": -0.5891016200294555,
        "description": "INTC 03/06/2026 54.00 P"
      },
      "call_candidates": 152,
      "put_candidates": 152,
      "warnings": [],
      "chain_error": null
    },
    {
      "ticker": "STX",
      "action": "Buy",
      "horizon": "swing_term",
      "thesis": "Medium-term trend with revenue/EPS growth, sector leadership, and supportive ownership.",
      "equity_entry": 348.26265,
      "underlying_price": 346.53,
      "best_call": {
        "put_call": "CALL",
        "symbol": "STX   260220C00347500",
        "strike": 347.5,
        "expiration": "2026-02-20T21:00:00+00:00",
        "days_to_expiration": 28,
        "target_dte": 45,
        "bid": 28.4,
        "ask": 30.0,
        "mid": 29.2,
        "mark": 29.2,
        "last": 29.2,
        "open_interest": 10,
        "volume": null,
        "delta": 0.537,
        "gamma": 0.006,
        "theta": -0.501,
        "vega": 0.388,
        "rho": 0.125,
        "implied_volatility": 73.564,
        "in_the_money": false,
        "spread": 1.6000000000000014,
        "spread_pct": 5.479452054794526,
        "break_even": 376.7,
        "moneyness_pct": 0.27991804461374986,
        "description": "STX 02/20/2026 347.50 C"
      },
      "best_put": {
        "put_call": "PUT",
        "symbol": "STX   260220P00347500",
        "strike": 347.5,
        "expiration": "2026-02-20T21:00:00+00:00",
        "days_to_expiration": 28,
        "target_dte": 45,
        "bid": 27.8,
        "ask": 30.2,
        "mid": 29.0,
        "mark": 29.0,
        "last": 28.63,
        "open_interest": 10,
        "volume": null,
        "delta": -0.463,
        "gamma": 0.006,
        "theta": -0.494,
        "vega": 0.387,
        "rho": -0.141,
        "implied_volatility": 73.564,
        "in_the_money": true,
        "spread": 2.3999999999999986,
        "spread_pct": 8.275862068965512,
        "break_even": 318.5,
        "moneyness_pct": 0.27991804461374986,
        "description": "STX 02/20/2026 347.50 P"
      },
      "call_candidates": 120,
      "put_candidates": 120,
      "warnings": [],
      "chain_error": null
    },
    {
      "ticker": "RGLD",
      "action": "Buy",
      "horizon": "swing_term",
      "thesis": "Medium-term trend with revenue/EPS growth, sector leadership, and supportive ownership.",
      "equity_entry": 289.26915,
      "underlying_price": 287.83,
      "best_call": {
        "put_call": "CALL",
        "symbol": "RGLD  260320C00290000",
        "strike": 290.0,
        "expiration": "2026-03-20T20:00:00+00:00",
        "days_to_expiration": 56,
        "target_dte": 45,
        "bid": 19.2,
        "ask": 21.6,
        "mid": 20.4,
        "mark": 20.4,
        "last": 20.3,
        "open_interest": 36,
        "volume": null,
        "delta": 0.529,
        "gamma": 0.008,
        "theta": -0.181,
        "vega": 0.454,
        "rho": 0.208,
        "implied_volatility": 42.091,
        "in_the_money": false,
        "spread": 2.400000000000002,
        "spread_pct": 11.764705882352953,
        "break_even": 310.4,
        "moneyness_pct": 0.753917242816946,
        "description": "RGLD 03/20/2026 290.00 C"
      },
      "best_put": {
        "put_call": "PUT",
        "symbol": "RGLD  260320P00290000",
        "strike": 290.0,
        "expiration": "2026-03-20T20:00:00+00:00",
        "days_to_expiration": 56,
        "target_dte": 45,
        "bid": 18.1,
        "ask": 21.1,
        "mid": 19.6,
        "mark": 19.6,
        "last": 18.5,
        "open_interest": 6,
        "volume": null,
        "delta": -0.477,
        "gamma": 0.008,
        "theta": -0.158,
        "vega": 0.454,
        "rho": -0.226,
        "implied_volatility": 42.091,
        "in_the_money": true,
        "spread": 3.0,
        "spread_pct": 15.30612244897959,
        "break_even": 270.4,
        "moneyness_pct": 0.753917242816946,
        "description": "RGLD 03/20/2026 290.00 P"
      },
      "call_candidates": 72,
      "put_candidates": 72,
      "warnings": [],
      "chain_error": null
    },
    {
      "ticker": "WDC",
      "action": "Buy",
      "horizon": "swing_term",
      "thesis": "Medium-term trend with revenue/EPS growth, sector leadership, and supportive ownership.",
      "equity_entry": 244.50645,
      "underlying_price": 243.29,
      "best_call": {
        "put_call": "CALL",
        "symbol": "WDC   260220C00242500",
        "strike": 242.5,
        "expiration": "2026-02-20T21:00:00+00:00",
        "days_to_expiration": 28,
        "target_dte": 45,
        "bid": 22.45,
        "ask": 25.4,
        "mid": 23.924999999999997,
        "mark": 23.92,
        "last": 23.64,
        "open_interest": 18,
        "volume": null,
        "delta": 0.551,
        "gamma": 0.007,
        "theta": -0.396,
        "vega": 0.27,
        "rho": 0.083,
        "implied_volatility": 84.132,
        "in_the_money": true,
        "spread": 2.9499999999999993,
        "spread_pct": 12.330198537095088,
        "break_even": 266.425,
        "moneyness_pct": -0.3247153602696338,
        "description": "WDC 02/20/2026 242.50 C"
      },
      "best_put": {
        "put_call": "PUT",
        "symbol": "WDC   260220P00242500",
        "strike": 242.5,
        "expiration": "2026-02-20T21:00:00+00:00",
        "days_to_expiration": 28,
        "target_dte": 45,
        "bid": 20.8,
        "ask": 24.25,
        "mid": 22.525,
        "mark": 22.53,
        "last": 23.01,
        "open_interest": 5,
        "volume": null,
        "delta": -0.448,
        "gamma": 0.007,
        "theta": -0.398,
        "vega": 0.271,
        "rho": -0.104,
        "implied_volatility": 84.132,
        "in_the_money": false,
        "spread": 3.4499999999999993,
        "spread_pct": 15.31631520532741,
        "break_even": 219.975,
        "moneyness_pct": -0.3247153602696338,
        "description": "WDC 02/20/2026 242.50 P"
      },
      "call_candidates": 120,
      "put_candidates": 120,
      "warnings": [],
      "chain_error": null
    },
    {
      "ticker": "AMTM",
      "action": "Buy",
      "horizon": "swing_term",
      "thesis": "Medium-term trend with revenue/EPS growth, sector leadership, and supportive ownership.",
      "equity_entry": 35.7378,
      "underlying_price": 35.56,
      "best_call": {
        "put_call": "CALL",
        "symbol": "AMTM  260320C00035000",
        "strike": 35.0,
        "expiration": "2026-03-20T20:00:00+00:00",
        "days_to_expiration": 56,
        "target_dte": 45,
        "bid": 2.95,
        "ask": 3.2,
        "mid": 3.075,
        "mark": 3.08,
        "last": 3.1,
        "open_interest": 96,
        "volume": null,
        "delta": 0.572,
        "gamma": 0.06,
        "theta": -0.023,
        "vega": 0.055,
        "rho": 0.027,
        "implied_volatility": 46.514,
        "in_the_money": true,
        "spread": 0.25,
        "spread_pct": 8.130081300813007,
        "break_even": 38.075,
        "moneyness_pct": -1.5748031496063055,
        "description": "AMTM 03/20/2026 35.00 C"
      },
      "best_put": {
        "put_call": "PUT",
        "symbol": "AMTM  260320P00035000",
        "strike": 35.0,
        "expiration": "2026-03-20T20:00:00+00:00",
        "days_to_expiration": 56,
        "target_dte": 45,
        "bid": 2.2,
        "ask": 2.4,
        "mid": 2.3,
        "mark": 2.3,
        "last": 2.8,
        "open_interest": 57,
        "volume": null,
        "delta": -0.428,
        "gamma": 0.06,
        "theta": -0.022,
        "vega": 0.055,
        "rho": -0.026,
        "implied_volatility": 46.514,
        "in_the_money": false,
        "spread": 0.19999999999999973,
        "spread_pct": 8.695652173913032,
        "break_even": 32.7,
        "moneyness_pct": -1.5748031496063055,
        "description": "AMTM 03/20/2026 35.00 P"
      },
      "call_candidates": 48,
      "put_candidates": 48,
      "warnings": [],
      "chain_error": null
    },
    {
      "ticker": "FTI",
      "action": "Buy",
      "horizon": "swing_term",
      "thesis": "Medium-term trend with revenue/EPS growth, sector leadership, and supportive ownership.",
      "equity_entry": 54.23985,
      "underlying_price": 53.97,
      "best_call": {
        "put_call": "CALL",
        "symbol": "FTI   260320C00055000",
        "strike": 55.0,
        "expiration": "2026-03-20T20:00:00+00:00",
        "days_to_expiration": 56,
        "target_dte": 45,
        "bid": 2.35,
        "ask": 2.9,
        "mid": 2.625,
        "mark": 2.63,
        "last": 2.6,
        "open_interest": 19,
        "volume": null,
        "delta": 0.472,
        "gamma": 0.051,
        "theta": -0.027,
        "vega": 0.085,
        "rho": 0.034,
        "implied_volatility": 36.857,
        "in_the_money": false,
        "spread": 0.5499999999999998,
        "spread_pct": 20.952380952380945,
        "break_even": 57.625,
        "moneyness_pct": 1.9084676672225334,
        "description": "FTI 03/20/2026 55.00 C"
      },
      "best_put": {
        "put_call": "PUT",
        "symbol": "FTI   260320P00055000",
        "strike": 55.0,
        "expiration": "2026-03-20T20:00:00+00:00",
        "days_to_expiration": 56,
        "target_dte": 45,
        "bid": 3.2,
        "ask": 3.7,
        "mid": 3.45,
        "mark": 3.45,
        "last": 0.0,
        "open_interest": 0,
        "volume": null,
        "delta": -0.527,
        "gamma": 0.051,
        "theta": -0.028,
        "vega": 0.085,
        "rho": -0.05,
        "implied_volatility": 36.857,
        "in_the_money": true,
        "spread": 0.5,
        "spread_pct": 14.492753623188406,
        "break_even": 51.55,
        "moneyness_pct": 1.9084676672225334,
        "description": "FTI 03/20/2026 55.00 P"
      },
      "call_candidates": 40,
      "put_candidates": 40,
      "warnings": [],
      "chain_error": null
    },
    {
      "ticker": "MTSI",
      "action": "Buy",
      "horizon": "swing_term",
      "thesis": "Medium-term trend with revenue/EPS growth, sector leadership, and supportive ownership.",
      "equity_entry": 225.41145,
      "underlying_price": 224.29,
      "best_call": {
        "put_call": "CALL",
        "symbol": "MTSI  260320C00220000",
        "strike": 220.0,
        "expiration": "2026-03-20T20:00:00+00:00",
        "days_to_expiration": 56,
        "target_dte": 45,
        "bid": 19.5,
        "ask": 22.4,
        "mid": 20.95,
        "mark": 20.95,
        "last": 0.0,
        "open_interest": 0,
        "volume": null,
        "delta": 0.578,
        "gamma": 0.009,
        "theta": -0.154,
        "vega": 0.346,
        "rho": 0.171,
        "implied_volatility": 50.075,
        "in_the_money": true,
        "spread": 2.8999999999999986,
        "spread_pct": 13.842482100238657,
        "break_even": 240.95,
        "moneyness_pct": -1.9127023050514922,
        "description": "MTSI 03/20/2026 220.00 C"
      },
      "best_put": {
        "put_call": "PUT",
        "symbol": "MTSI  260320P00220000",
        "strike": 220.0,
        "expiration": "2026-03-20T20:00:00+00:00",
        "days_to_expiration": 56,
        "target_dte": 45,
        "bid": 14.0,
        "ask": 16.8,
        "mid": 15.4,
        "mark": 15.4,
        "last": 15.8,
        "open_interest": 1,
        "volume": null,
        "delta": -0.422,
        "gamma": 0.009,
        "theta": -0.153,
        "vega": 0.346,
        "rho": -0.163,
        "implied_volatility": 50.075,
        "in_the_money": false,
        "spread": 2.8000000000000007,
        "spread_pct": 18.181818181818183,
        "break_even": 204.6,
        "moneyness_pct": -1.9127023050514922,
        "description": "MTSI 03/20/2026 220.00 P"
      },
      "call_candidates": 40,
      "put_candidates": 40,
      "warnings": [],
      "chain_error": null
    },
    {
      "ticker": "AMAT",
      "action": "Buy",
      "horizon": "swing_term",
      "thesis": "Medium-term trend with revenue/EPS growth, sector leadership, and supportive ownership.",
      "equity_entry": 320.378925,
      "underlying_price": 318.785,
      "best_call": {
        "put_call": "CALL",
        "symbol": "AMAT  260306C00320000",
        "strike": 320.0,
        "expiration": "2026-03-06T21:00:00+00:00",
        "days_to_expiration": 42,
        "target_dte": 45,
        "bid": 19.9,
        "ask": 23.1,
        "mid": 21.5,
        "mark": 21.5,
        "last": 21.21,
        "open_interest": 2,
        "volume": null,
        "delta": 0.524,
        "gamma": 0.008,
        "theta": -0.243,
        "vega": 0.435,
        "rho": 0.172,
        "implied_volatility": 47.54,
        "in_the_money": false,
        "spread": 3.200000000000003,
        "spread_pct": 14.883720930232572,
        "break_even": 341.5,
        "moneyness_pct": 0.3811346205122496,
        "description": "AMAT 03/06/2026 320.00 C"
      },
      "best_put": {
        "put_call": "PUT",
        "symbol": "AMAT  260306P00320000",
        "strike": 320.0,
        "expiration": "2026-03-06T21:00:00+00:00",
        "days_to_expiration": 42,
        "target_dte": 45,
        "bid": 19.65,
        "ask": 23.0,
        "mid": 21.325,
        "mark": 21.33,
        "last": 0.0,
        "open_interest": 0,
        "volume": null,
        "delta": -0.476,
        "gamma": 0.008,
        "theta": -0.242,
        "vega": 0.435,
        "rho": -0.193,
        "implied_volatility": 47.54,
        "in_the_money": true,
        "spread": 3.3500000000000014,
        "spread_pct": 15.709261430246196,
        "break_even": 298.675,
        "moneyness_pct": 0.3811346205122496,
        "description": "AMAT 03/06/2026 320.00 P"
      },
      "call_candidates": 152,
      "put_candidates": 152,
      "warnings": [],
      "chain_error": null
    },
    {
      "ticker": "KEX",
      "action": "Buy",
      "horizon": "swing_term",
      "thesis": "Medium-term trend with revenue/EPS growth, sector leadership, and supportive ownership.",
      "equity_entry": 131.36355,
      "underlying_price": 130.71,
      "best_call": {
        "put_call": "CALL",
        "symbol": "KEX   260320C00130000",
        "strike": 130.0,
        "expiration": "2026-03-20T20:00:00+00:00",
        "days_to_expiration": 56,
        "target_dte": 45,
        "bid": 4.9,
        "ask": 9.0,
        "mid": 6.95,
        "mark": 6.95,
        "last": 5.3,
        "open_interest": 60,
        "volume": null,
        "delta": 0.529,
        "gamma": 0.026,
        "theta": -0.05,
        "vega": 0.204,
        "rho": 0.091,
        "implied_volatility": 30.004,
        "in_the_money": true,
        "spread": 4.1,
        "spread_pct": 58.99280575539567,
        "break_even": 136.95,
        "moneyness_pct": -0.5431872083237762,
        "description": "KEX 03/20/2026 130.00 C"
      },
      "best_put": {
        "put_call": "PUT",
        "symbol": "KEX   260320P00130000",
        "strike": 130.0,
        "expiration": "2026-03-20T20:00:00+00:00",
        "days_to_expiration": 56,
        "target_dte": 45,
        "bid": 4.2,
        "ask": 7.9,
        "mid": 6.050000000000001,
        "mark": 6.05,
        "last": 5.7,
        "open_interest": 1,
        "volume": null,
        "delta": -0.47,
        "gamma": 0.026,
        "theta": -0.059,
        "vega": 0.204,
        "rho": -0.105,
        "implied_volatility": 30.004,
        "in_the_money": false,
        "spread": 3.7,
        "spread_pct": 61.15702479338842,
        "break_even": 123.95,
        "moneyness_pct": -0.5431872083237762,
        "description": "KEX 03/20/2026 130.00 P"
      },
      "call_candidates": 32,
      "put_candidates": 32,
      "warnings": [],
      "chain_error": null
    }
  ],
  "meta": {
    "horizon": "swing_term",
    "limit": 10,
    "strike_count": 8,
    "include_puts": true,
    "range": "NTM",
    "stock_list": "mass_combo",
    "stock_list_label": "Mass combo (S&P 500 + NASDAQ-100 + Russell 2000)",
    "suggestions_count": 12,
    "generated_at": "2026-01-23T12:51:12.596081+00:00"
  }
}